{
  "cardName": "최종시험",
  "cardDescription": "무작위 아군에게 +5/+5을 주고, 전기기사 김현조를 내 손으로 가져옵니다.",
  "cardIdNum": 123,
  "cost": 5,
  "cardClass": 1,
  "cardType": 1,
  "cardRarity": 0,
  "associatedHandler": null,
  "evtDatas": [
    {
      "$type": "BuffHandler, Assembly-CSharp",
      "buffTargeting": 2,
      "buffType": 2,
      "buffExtraArea": 0,
      "buffFX": 0,
      "relatedIds": [],
      "buffAtt": 5,
      "buffHp": 5,
      "drawCount": 0,
      "when": 0,
      "area": 5,
      "type": 0
    },
    {
      "$type": "UtillHandler, Assembly-CSharp",
      "utillType": 2,
      "relatedCards": [
        124
      ],
      "utillAmount": 0,
      "when": 0,
      "area": 0,
      "type": 3
    }
  ]
}